{
  "metadata" : {
    "identifier" : "https://www.nettruyenio.com/truyen-tranh/bao-ve-sieu-sao-cua-toi-261650",
    "title" : "Bảo Vệ Siêu Sao Của Tôi - Chapter 36",
    "subtitle" : null,
    "author" : null,
    "narrator" : null,
    "language" : "vi",
    "description" : null,
    "publisher" : "N/A",
    "subject" : null,
    "modified" : null,
    "published" : "2023-08-24",
    "duration" : 0,
    "abridged" : false,
    "conformsTo" : "https://readium.org/webpub-manifest/profiles/divina",
    "numberOfPages" : 143,
    "readingProgression" : "ttb",
    "belongsTo" : null,
    "presentation" : {
      "fit" : "width",
      "overflow" : "scrolled",
      "continuous" : true
    },
    "@type" : null,
    "schema:license" : null
  },
  "links" : [ {
    "rel" : "self",
    "href" : "https://raw.githubusercontent.com/thuvienonline40/book_storage_collection/main/comic_manifest.json",
    "type" : "application/divina+json"
  } ],
  "readingOrder" : [ {
    "href" : "https://raw.githubusercontent.com/tsvhcomic23/comic_storage3/main/IMAGE/IMAGE_65c7eaf823a03d4562a1dbb1606a45aa_e39ecb8f822aec61106e509ceb750706_62d9bef82259eac1f7ead91f707dbd76.jpg",
    "type" : "image/jpeg",
    "bitrate" : 0,
    "duration" : 0,
    "title" : null,
    "properties" : null,
    "alternate" : [ {
      "href" : "https://i8.ntcdntempv3.com/data/images/26165/656919/001.jpg?data=net",
      "type" : "image/jpeg",
      "bitrate" : 0,
      "duration" : 0,
      "title" : null,
      "properties" : null,
      "alternate" : null
    } ]
  }, {
    "href" : "https://raw.githubusercontent.com/tsvhcomic23/comic_storage3/main/IMAGE/IMAGE_65c7eaf823a03d4562a1dbb1606a45aa_e39ecb8f822aec61106e509ceb750706_a056d0b245c5a666d1687985d8937ff1.jpg",
    "type" : "image/jpeg",
    "bitrate" : 0,
    "duration" : 0,
    "title" : null,
    "properties" : null,
    "alternate" : [ {
      "href" : "https://i8.ntcdntempv3.com/data/images/26165/656919/002.jpg?data=net",
      "type" : "image/jpeg",
      "bitrate" : 0,
      "duration" : 0,
      "title" : null,
      "properties" : null,
      "alternate" : null
    } ]
  }, {
    "href" : "https://raw.githubusercontent.com/tsvhcomic23/comic_storage3/main/IMAGE/IMAGE_65c7eaf823a03d4562a1dbb1606a45aa_e39ecb8f822aec61106e509ceb750706_3280545458a052836d8b98913523629b.jpg",
    "type" : "image/jpeg",
    "bitrate" : 0,
    "duration" : 0,
    "title" : null,
    "properties" : null,
    "alternate" : [ {
      "href" : "https://i8.ntcdntempv3.com/data/images/26165/656919/003.jpg?data=net",
      "type" : "image/jpeg",
      "bitrate" : 0,
      "duration" : 0,
      "title" : null,
      "properties" : null,
      "alternate" : null
    } ]
  }, {
    "href" : "https://raw.githubusercontent.com/tsvhcomic23/comic_storage3/main/IMAGE/IMAGE_65c7eaf823a03d4562a1dbb1606a45aa_e39ecb8f822aec61106e509ceb750706_cb321102abda2897eb8514bd9ed5f171.jpg",
    "type" : "image/jpeg",
    "bitrate" : 0,
    "duration" : 0,
    "title" : null,
    "properties" : null,
    "alternate" : [ {
      "href" : "https://i8.ntcdntempv3.com/data/images/26165/656919/004.jpg?data=net",
      "type" : "image/jpeg",
      "bitrate" : 0,
      "duration" : 0,
      "title" : null,
      "properties" : null,
      "alternate" : null
    } ]
  }, {
    "href" : "https://raw.githubusercontent.com/tsvhcomic23/comic_storage3/main/IMAGE/IMAGE_65c7eaf823a03d4562a1dbb1606a45aa_e39ecb8f822aec61106e509ceb750706_6b8baf73605dcaed277c1ffcab330641.jpg",
    "type" : "image/jpeg",
    "bitrate" : 0,
    "duration" : 0,
    "title" : null,
    "properties" : null,
    "alternate" : [ {
      "href" : "https://i8.ntcdntempv3.com/data/images/26165/656919/005.jpg?data=net",
      "type" : "image/jpeg",
      "bitrate" : 0,
      "duration" : 0,
      "title" : null,
      "properties" : null,
      "alternate" : null
    } ]
  }, {
    "href" : "https://raw.githubusercontent.com/tsvhcomic23/comic_storage3/main/IMAGE/IMAGE_65c7eaf823a03d4562a1dbb1606a45aa_e39ecb8f822aec61106e509ceb750706_aa650b3f84bd723ee54b40da7ffa6553.jpg",
    "type" : "image/jpeg",
    "bitrate" : 0,
    "duration" : 0,
    "title" : null,
    "properties" : null,
    "alternate" : [ {
      "href" : "https://i8.ntcdntempv3.com/data/images/26165/656919/006.jpg?data=net",
      "type" : "image/jpeg",
      "bitrate" : 0,
      "duration" : 0,
      "title" : null,
      "properties" : null,
      "alternate" : null
    } ]
  }, {
    "href" : "https://raw.githubusercontent.com/tsvhcomic23/comic_storage3/main/IMAGE/IMAGE_65c7eaf823a03d4562a1dbb1606a45aa_e39ecb8f822aec61106e509ceb750706_c06b02a9e2ec708583f4b0f6b057adfb.jpg",
    "type" : "image/jpeg",
    "bitrate" : 0,
    "duration" : 0,
    "title" : null,
    "properties" : null,
    "alternate" : [ {
      "href" : "https://i8.ntcdntempv3.com/data/images/26165/656919/007.jpg?data=net",
      "type" : "image/jpeg",
      "bitrate" : 0,
      "duration" : 0,
      "title" : null,
      "properties" : null,
      "alternate" : null
    } ]
  }, {
    "href" : "https://raw.githubusercontent.com/tsvhcomic23/comic_storage3/main/IMAGE/IMAGE_65c7eaf823a03d4562a1dbb1606a45aa_e39ecb8f822aec61106e509ceb750706_ac9d423196ab9cfe752c8ac1cca42ca0.jpg",
    "type" : "image/jpeg",
    "bitrate" : 0,
    "duration" : 0,
    "title" : null,
    "properties" : null,
    "alternate" : [ {
      "href" : "https://i8.ntcdntempv3.com/data/images/26165/656919/008.jpg?data=net",
      "type" : "image/jpeg",
      "bitrate" : 0,
      "duration" : 0,
      "title" : null,
      "properties" : null,
      "alternate" : null
    } ]
  }, {
    "href" : "https://raw.githubusercontent.com/tsvhcomic23/comic_storage3/main/IMAGE/IMAGE_65c7eaf823a03d4562a1dbb1606a45aa_e39ecb8f822aec61106e509ceb750706_864e71aa9cd988b86d3c27734fee9616.jpg",
    "type" : "image/jpeg",
    "bitrate" : 0,
    "duration" : 0,
    "title" : null,
    "properties" : null,
    "alternate" : [ {
      "href" : "https://i8.ntcdntempv3.com/data/images/26165/656919/009.jpg?data=net",
      "type" : "image/jpeg",
      "bitrate" : 0,
      "duration" : 0,
      "title" : null,
      "properties" : null,
      "alternate" : null
    } ]
  }, {
    "href" : "https://raw.githubusercontent.com/tsvhcomic23/comic_storage3/main/IMAGE/IMAGE_65c7eaf823a03d4562a1dbb1606a45aa_e39ecb8f822aec61106e509ceb750706_21988950323b0d503ed05b2491347e98.jpg",
    "type" : "image/jpeg",
    "bitrate" : 0,
    "duration" : 0,
    "title" : null,
    "properties" : null,
    "alternate" : [ {
      "href" : "https://i8.ntcdntempv3.com/data/images/26165/656919/010.jpg?data=net",
      "type" : "image/jpeg",
      "bitrate" : 0,
      "duration" : 0,
      "title" : null,
      "properties" : null,
      "alternate" : null
    } ]
  }, {
    "href" : "https://raw.githubusercontent.com/tsvhcomic23/comic_storage3/main/IMAGE/IMAGE_65c7eaf823a03d4562a1dbb1606a45aa_e39ecb8f822aec61106e509ceb750706_1516ab964797e398184536f2ac7cbf69.jpg",
    "type" : "image/jpeg",
    "bitrate" : 0,
    "duration" : 0,
    "title" : null,
    "properties" : null,
    "alternate" : [ {
      "href" : "https://i8.ntcdntempv3.com/data/images/26165/656919/011.jpg?data=net",
      "type" : "image/jpeg",
      "bitrate" : 0,
      "duration" : 0,
      "title" : null,
      "properties" : null,
      "alternate" : null
    } ]
  }, {
    "href" : "https://raw.githubusercontent.com/tsvhcomic23/comic_storage3/main/IMAGE/IMAGE_65c7eaf823a03d4562a1dbb1606a45aa_e39ecb8f822aec61106e509ceb750706_e2819a1c0faaedc6112a09b450085af4.jpg",
    "type" : "image/jpeg",
    "bitrate" : 0,
    "duration" : 0,
    "title" : null,
    "properties" : null,
    "alternate" : [ {
      "href" : "https://i8.ntcdntempv3.com/data/images/26165/656919/012.jpg?data=net",
      "type" : "image/jpeg",
      "bitrate" : 0,
      "duration" : 0,
      "title" : null,
      "properties" : null,
      "alternate" : null
    } ]
  }, {
    "href" : "https://raw.githubusercontent.com/tsvhcomic23/comic_storage3/main/IMAGE/IMAGE_65c7eaf823a03d4562a1dbb1606a45aa_e39ecb8f822aec61106e509ceb750706_8decda5bae5fe74b7ffe370004ab7ba2.jpg",
    "type" : "image/jpeg",
    "bitrate" : 0,
    "duration" : 0,
    "title" : null,
    "properties" : null,
    "alternate" : [ {
      "href" : "https://i8.ntcdntempv3.com/data/images/26165/656919/013.jpg?data=net",
      "type" : "image/jpeg",
      "bitrate" : 0,
      "duration" : 0,
      "title" : null,
      "properties" : null,
      "alternate" : null
    } ]
  }, {
    "href" : "https://raw.githubusercontent.com/tsvhcomic23/comic_storage3/main/IMAGE/IMAGE_65c7eaf823a03d4562a1dbb1606a45aa_e39ecb8f822aec61106e509ceb750706_c541a9542f47d453eb013dde1ea74456.jpg",
    "type" : "image/jpeg",
    "bitrate" : 0,
    "duration" : 0,
    "title" : null,
    "properties" : null,
    "alternate" : [ {
      "href" : "https://i8.ntcdntempv3.com/data/images/26165/656919/014.jpg?data=net",
      "type" : "image/jpeg",
      "bitrate" : 0,
      "duration" : 0,
      "title" : null,
      "properties" : null,
      "alternate" : null
    } ]
  }, {
    "href" : "https://raw.githubusercontent.com/tsvhcomic23/comic_storage3/main/IMAGE/IMAGE_65c7eaf823a03d4562a1dbb1606a45aa_e39ecb8f822aec61106e509ceb750706_61bf6fa1abc66cb8c388df1ad51046b5.jpg",
    "type" : "image/jpeg",
    "bitrate" : 0,
    "duration" : 0,
    "title" : null,
    "properties" : null,
    "alternate" : [ {
      "href" : "https://i8.ntcdntempv3.com/data/images/26165/656919/015.jpg?data=net",
      "type" : "image/jpeg",
      "bitrate" : 0,
      "duration" : 0,
      "title" : null,
      "properties" : null,
      "alternate" : null
    } ]
  }, {
    "href" : "https://raw.githubusercontent.com/tsvhcomic23/comic_storage3/main/IMAGE/IMAGE_65c7eaf823a03d4562a1dbb1606a45aa_e39ecb8f822aec61106e509ceb750706_1c4c17733e76514d391721fa18a64e90.jpg",
    "type" : "image/jpeg",
    "bitrate" : 0,
    "duration" : 0,
    "title" : null,
    "properties" : null,
    "alternate" : [ {
      "href" : "https://i8.ntcdntempv3.com/data/images/26165/656919/016.jpg?data=net",
      "type" : "image/jpeg",
      "bitrate" : 0,
      "duration" : 0,
      "title" : null,
      "properties" : null,
      "alternate" : null
    } ]
  }, {
    "href" : "https://raw.githubusercontent.com/tsvhcomic23/comic_storage3/main/IMAGE/IMAGE_65c7eaf823a03d4562a1dbb1606a45aa_e39ecb8f822aec61106e509ceb750706_04ed4f57929e6582a87fcd1239830d0f.jpg",
    "type" : "image/jpeg",
    "bitrate" : 0,
    "duration" : 0,
    "title" : null,
    "properties" : null,
    "alternate" : [ {
      "href" : "https://i8.ntcdntempv3.com/data/images/26165/656919/017.jpg?data=net",
      "type" : "image/jpeg",
      "bitrate" : 0,
      "duration" : 0,
      "title" : null,
      "properties" : null,
      "alternate" : null
    } ]
  }, {
    "href" : "https://raw.githubusercontent.com/tsvhcomic23/comic_storage3/main/IMAGE/IMAGE_65c7eaf823a03d4562a1dbb1606a45aa_e39ecb8f822aec61106e509ceb750706_a62093d24b9f24925fba760b8f54dcf1.jpg",
    "type" : "image/jpeg",
    "bitrate" : 0,
    "duration" : 0,
    "title" : null,
    "properties" : null,
    "alternate" : [ {
      "href" : "https://i8.ntcdntempv3.com/data/images/26165/656919/018.jpg?data=net",
      "type" : "image/jpeg",
      "bitrate" : 0,
      "duration" : 0,
      "title" : null,
      "properties" : null,
      "alternate" : null
    } ]
  }, {
    "href" : "https://raw.githubusercontent.com/tsvhcomic23/comic_storage3/main/IMAGE/IMAGE_65c7eaf823a03d4562a1dbb1606a45aa_e39ecb8f822aec61106e509ceb750706_7927ea840baf45ebfe4c27a60b4d90ea.jpg",
    "type" : "image/jpeg",
    "bitrate" : 0,
    "duration" : 0,
    "title" : null,
    "properties" : null,
    "alternate" : [ {
      "href" : "https://i8.ntcdntempv3.com/data/images/26165/656919/019.jpg?data=net",
      "type" : "image/jpeg",
      "bitrate" : 0,
      "duration" : 0,
      "title" : null,
      "properties" : null,
      "alternate" : null
    } ]
  }, {
    "href" : "https://raw.githubusercontent.com/tsvhcomic23/comic_storage3/main/IMAGE/IMAGE_65c7eaf823a03d4562a1dbb1606a45aa_e39ecb8f822aec61106e509ceb750706_2981e5c96680c9bfd739c44355dfd199.jpg",
    "type" : "image/jpeg",
    "bitrate" : 0,
    "duration" : 0,
    "title" : null,
    "properties" : null,
    "alternate" : [ {
      "href" : "https://i8.ntcdntempv3.com/data/images/26165/656919/020.jpg?data=net",
      "type" : "image/jpeg",
      "bitrate" : 0,
      "duration" : 0,
      "title" : null,
      "properties" : null,
      "alternate" : null
    } ]
  }, {
    "href" : "https://raw.githubusercontent.com/tsvhcomic23/comic_storage3/main/IMAGE/IMAGE_65c7eaf823a03d4562a1dbb1606a45aa_e39ecb8f822aec61106e509ceb750706_e5f21fe072669d6ca30f5beac3f707c0.jpg",
    "type" : "image/jpeg",
    "bitrate" : 0,
    "duration" : 0,
    "title" : null,
    "properties" : null,
    "alternate" : [ {
      "href" : "https://i8.ntcdntempv3.com/data/images/26165/656919/021.jpg?data=net",
      "type" : "image/jpeg",
      "bitrate" : 0,
      "duration" : 0,
      "title" : null,
      "properties" : null,
      "alternate" : null
    } ]
  }, {
    "href" : "https://raw.githubusercontent.com/tsvhcomic23/comic_storage3/main/IMAGE/IMAGE_65c7eaf823a03d4562a1dbb1606a45aa_e39ecb8f822aec61106e509ceb750706_ba100370a7af4f7de2f8849a64588f9c.jpg",
    "type" : "image/jpeg",
    "bitrate" : 0,
    "duration" : 0,
    "title" : null,
    "properties" : null,
    "alternate" : [ {
      "href" : "https://i8.ntcdntempv3.com/data/images/26165/656919/022.jpg?data=net",
      "type" : "image/jpeg",
      "bitrate" : 0,
      "duration" : 0,
      "title" : null,
      "properties" : null,
      "alternate" : null
    } ]
  }, {
    "href" : "https://raw.githubusercontent.com/tsvhcomic23/comic_storage3/main/IMAGE/IMAGE_65c7eaf823a03d4562a1dbb1606a45aa_e39ecb8f822aec61106e509ceb750706_f7a7da74ec14cefdee6a56f766f05041.jpg",
    "type" : "image/jpeg",
    "bitrate" : 0,
    "duration" : 0,
    "title" : null,
    "properties" : null,
    "alternate" : [ {
      "href" : "https://i8.ntcdntempv3.com/data/images/26165/656919/023.jpg?data=net",
      "type" : "image/jpeg",
      "bitrate" : 0,
      "duration" : 0,
      "title" : null,
      "properties" : null,
      "alternate" : null
    } ]
  }, {
    "href" : "https://raw.githubusercontent.com/tsvhcomic23/comic_storage3/main/IMAGE/IMAGE_65c7eaf823a03d4562a1dbb1606a45aa_e39ecb8f822aec61106e509ceb750706_5dd56e64484a733b731039378419b0ea.jpg",
    "type" : "image/jpeg",
    "bitrate" : 0,
    "duration" : 0,
    "title" : null,
    "properties" : null,
    "alternate" : [ {
      "href" : "https://i8.ntcdntempv3.com/data/images/26165/656919/024.jpg?data=net",
      "type" : "image/jpeg",
      "bitrate" : 0,
      "duration" : 0,
      "title" : null,
      "properties" : null,
      "alternate" : null
    } ]
  }, {
    "href" : "https://raw.githubusercontent.com/tsvhcomic23/comic_storage3/main/IMAGE/IMAGE_65c7eaf823a03d4562a1dbb1606a45aa_e39ecb8f822aec61106e509ceb750706_add5dbf36da84700f14c22ad81a3e86b.jpg",
    "type" : "image/jpeg",
    "bitrate" : 0,
    "duration" : 0,
    "title" : null,
    "properties" : null,
    "alternate" : [ {
      "href" : "https://i8.ntcdntempv3.com/data/images/26165/656919/025.jpg?data=net",
      "type" : "image/jpeg",
      "bitrate" : 0,
      "duration" : 0,
      "title" : null,
      "properties" : null,
      "alternate" : null
    } ]
  }, {
    "href" : "https://raw.githubusercontent.com/tsvhcomic23/comic_storage3/main/IMAGE/IMAGE_65c7eaf823a03d4562a1dbb1606a45aa_e39ecb8f822aec61106e509ceb750706_ba321ec5db6c203f73a36c44797d24ec.jpg",
    "type" : "image/jpeg",
    "bitrate" : 0,
    "duration" : 0,
    "title" : null,
    "properties" : null,
    "alternate" : [ {
      "href" : "https://i8.ntcdntempv3.com/data/images/26165/656919/026.jpg?data=net",
      "type" : "image/jpeg",
      "bitrate" : 0,
      "duration" : 0,
      "title" : null,
      "properties" : null,
      "alternate" : null
    } ]
  } ],
  "toc" : null,
  "@context" : "https://readium.org/webpub-manifest/context.jsonld"
}